<?xml version="1.0" encoding="utf-8" ?><dwsync><file name="editable_selects.js" server="digital.ltd.uk//www/vhtdocs/digital/" local="3488362736" remote="12077686652" Dst="-1" /><file name="form_utils.js" server="digital.ltd.uk//www/vhtdocs/digital/" local="3488362744" remote="12077686652" Dst="-1" /><file name="mctabs.js" server="digital.ltd.uk//www/vhtdocs/digital/" local="3488362746" remote="12077686652" Dst="-1" /><file name="validate.js" server="digital.ltd.uk//www/vhtdocs/digital/" local="3488362755" remote="12077686652" Dst="-1" /><file name="editable_selects.js" server="ftp.aroragroup.co.uk//" local="3488362736" remote="12078363212" Dst="-1" /><file name="form_utils.js" server="ftp.aroragroup.co.uk//" local="3488362744" remote="12078363212" Dst="-1" /><file name="mctabs.js" server="ftp.aroragroup.co.uk//" local="3488362746" remote="12078363212" Dst="-1" /><file name="validate.js" server="ftp.aroragroup.co.uk//" local="3488362755" remote="12078363212" Dst="-1" /></dwsync>